Metadata-Version: 2.1
Name: version-system-cli
Version: 1.0.0
Summary: Version control of your system
Author: Jeferson Lopes
Author-email: jefersonlopes.sjn@gmail.com
License: MIT License
Keywords: control version system
License-File: LICENCE
Requires-Dist: colorama
